spcfile/__init__.py
spcfile/spcfile.py
spcfile-0.1.0.dist-info/METADATA
spcfile-0.1.0.dist-info/WHEEL
spcfile-0.1.0.dist-info/licenses/LICENSE
spcfile-0.1.0.dist-info/RECORD
